git_dummy/__init__.py
git_dummy/__main__.py
git_dummy/settings.py
git_dummy/util.py
git_dummy-0.1.2.dist-info/LICENSE
git_dummy-0.1.2.dist-info/METADATA
git_dummy-0.1.2.dist-info/WHEEL
git_dummy-0.1.2.dist-info/entry_points.txt
git_dummy-0.1.2.dist-info/top_level.txt
git_dummy-0.1.2.dist-info/RECORD
