Metadata-Version: 2.1
Name: git-dummy
Version: 0.1.2
Summary: Generate dummy Git repositories populated with the desired number of commits, branches, and structure.
Home-page: https://initialcommit.com/tools/git-dummy
Author: Jacob Stopak
Author-email: jacob@initialcommit.io
Project-URL: Homepage, https://initialcommit.com/tools/git-dummy
Project-URL: Source, https://github.com/initialcommit-com/git-dummy
Keywords: git dummy generate populate repo repository
Classifier: Programming Language :: Python :: 3
Classifier: License :: OSI Approved :: MIT License
Classifier: Operating System :: OS Independent
Requires-Python: >=3.7
License-File: LICENSE
Requires-Dist: gitpython
Requires-Dist: typer
Requires-Dist: pydantic-settings
